rro_env/__init__.py
rro_env/docker.py
rro_env/env.py
rro_env/utils.py
rro_env/datasets/cache_bill_map.json
rro_env/datasets/cache_consignor_map.json
rro_env/datasets/cache_main_data.json
rro_env-0.1.10.dist-info/METADATA
rro_env-0.1.10.dist-info/WHEEL
rro_env-0.1.10.dist-info/top_level.txt
rro_env-0.1.10.dist-info/RECORD
