Metadata-Version: 2.1
Name: rro_env
Version: 0.1.10
Summary: A Gym environment for 3D container relocation
Home-page: https://github.com/JNU-Tangyin/RRO
Author: Near Yip
Author-email: yiptsangkin@gmail.com
Keywords: CRP,3D,container relocation,RL,gym,environment
Requires-Dist: gymnasium
Requires-Dist: numpy
Requires-Dist: joblib
Requires-Dist: pandas
Requires-Dist: tqdm
Requires-Dist: dill
Requires-Dist: cachetools
